jnrbase/__init__.py
jnrbase/_version.py
jnrbase/attrdict.py
jnrbase/cmdline.py
jnrbase/colourise.py
jnrbase/config.py
jnrbase/context.py
jnrbase/debug.py
jnrbase/entry.py
jnrbase/git.py
jnrbase/human_time.py
jnrbase/i18n.py
jnrbase/iso_8601.py
jnrbase/json_datetime.py
jnrbase/pager.py
jnrbase/pip_support.py
jnrbase/template.py
jnrbase/timer.py
jnrbase/xdg_basedir.py
jnrbase-1.3.0.dist-info/COPYING
jnrbase-1.3.0.dist-info/METADATA
jnrbase-1.3.0.dist-info/WHEEL
jnrbase-1.3.0.dist-info/entry_points.txt
jnrbase-1.3.0.dist-info/top_level.txt
jnrbase-1.3.0.dist-info/zip-safe
jnrbase-1.3.0.dist-info/RECORD
