Metadata-Version: 2.1
Name: jnrbase
Version: 1.3.0
Summary: Common utility functionality
Home-page: https://github.com/JNRowe/jnrbase
Author: James Rowe
Author-email: jnrowe@gmail.com
License: GPL-3
Project-URL: Contributors, https://github.com/JNRowe/jnrbase/contributors/
Project-URL: Documentation, https://jnrbase.readthedocs.io/
Project-URL: Git repository, https://github.com/JNRowe/jnrbase/
Project-URL: Issue tracker, https://github.com/JNRowe/jnrbase/issues/
Keywords: library,support
Platform: UNKNOWN
Classifier: Development Status :: 5 - Production/Stable
Classifier: Intended Audience :: Developers
Classifier: License :: OSI Approved
Classifier: License :: OSI Approved :: GNU General Public License (GPL)
Classifier: License :: OSI Approved :: GNU General Public License v3 or later (GPLv3+)
Classifier: Natural Language :: English
Classifier: Operating System :: OS Independent
Classifier: Programming Language :: Python
Classifier: Programming Language :: Python :: 3
Classifier: Programming Language :: Python :: 3.6
Classifier: Programming Language :: Python :: 3.7
Classifier: Programming Language :: Python :: 3.8
Classifier: Programming Language :: Python :: 3 :: Only
Classifier: Programming Language :: Python :: Implementation
Classifier: Programming Language :: Python :: Implementation :: CPython
Classifier: Programming Language :: Python :: Implementation :: PyPy
Classifier: Topic :: Software Development
Classifier: Topic :: Software Development :: Libraries
Classifier: Topic :: Software Development :: Libraries :: Application Frameworks
Classifier: Topic :: Software Development :: Libraries :: Python Modules
Provides-Extra: cli
Requires-Dist: click (>=7.0) ; extra == 'cli'
Requires-Dist: ciso8601 (>=2.1) ; extra == 'cli'
Requires-Dist: html2text (>=2020.1.16) ; extra == 'cli'
Requires-Dist: Jinja2 (>=2.10.2) ; extra == 'cli'
Requires-Dist: Pygments (>=2.5) ; extra == 'cli'
Provides-Extra: colour
Requires-Dist: click (>=7.0) ; extra == 'colour'
Provides-Extra: iso_8601
Requires-Dist: ciso8601 (>=2.1) ; extra == 'iso_8601'
Provides-Extra: template
Requires-Dist: click (>=7.0) ; extra == 'template'
Requires-Dist: html2text (>=2020.1.16) ; extra == 'template'
Requires-Dist: Jinja2 (>=2.10.2) ; extra == 'template'
Requires-Dist: Pygments (>=2.5) ; extra == 'template'
